netbox_devicetype_importer/__init__.py
netbox_devicetype_importer/admin.py
netbox_devicetype_importer/filters.py
netbox_devicetype_importer/forms.py
netbox_devicetype_importer/models.py
netbox_devicetype_importer/navigation.py
netbox_devicetype_importer/signals.py
netbox_devicetype_importer/tables.py
netbox_devicetype_importer/template_content.py
netbox_devicetype_importer/urls.py
netbox_devicetype_importer/utilities.py
netbox_devicetype_importer/version.py
netbox_devicetype_importer/views.py
netbox_devicetype_importer/api/__init__.py
netbox_devicetype_importer/api/serializers.py
netbox_devicetype_importer/api/urls.py
netbox_devicetype_importer/api/views.py
netbox_devicetype_importer/migrations/0001_netbox_devicetype_importer.py
netbox_devicetype_importer/migrations/0002_netbox_devicetype_importer.py
netbox_devicetype_importer/migrations/0003_netbox_devicetype_importer.py
netbox_devicetype_importer/migrations/0004_netbox_devicetype_importer.py
netbox_devicetype_importer/migrations/0005_netbox_devicetype_importer.py
netbox_devicetype_importer/migrations/__init__.py
netbox_devicetype_importer/templates/netbox_devicetype_importer/metadevicetype_list.html
netbox_devicetype_importer-0.0.6.dist-info/LICENSE
netbox_devicetype_importer-0.0.6.dist-info/METADATA
netbox_devicetype_importer-0.0.6.dist-info/WHEEL
netbox_devicetype_importer-0.0.6.dist-info/top_level.txt
netbox_devicetype_importer-0.0.6.dist-info/RECORD
