Metadata-Version: 2.1
Name: netbox-devicetype-importer
Version: 0.0.6
Summary: Import DeviceTypes from github repo
Home-page: https://github.com/k01ek/netbox-devicetype-importer
Author: Nikolay Yuzefovich
Author-email: mgk.kolek@gmail.com
Classifier: Development Status :: 2 - Pre-Alpha
Classifier: Framework :: Django
Classifier: Programming Language :: Python :: 3
License-File: LICENSE
